{
  "name": "Gate Mode Demo",
  "description": "Demonstrates the 'gate' playback mode where sounds are cut at step boundaries. Ideal for sustained pads, drones, and rhythmic chopping effects. Compare with 'oneshot' tracks.",
  "tracks": [
    {
      "id": "kick-steady",
      "name": "Kick",
      "sampleId": "kick",
      "steps": [
        true, false, false, false, true, false, false, false, true, false, false, false, true, false, false, false
      ],
      "parameterLocks": [
        {"volume": 1.0}, null, null, null, {"volume": 0.9}, null, null, null, {"volume": 1.0}, null, null, null, {"volume": 0.9}, null, null, null
      ],
      "volume": 0.8,
      "muted": false,
      "playbackMode": "oneshot",
      "transpose": 0,
      "stepCount": 16
    },
    {
      "id": "pad-gated",
      "name": "Pad GATE",
      "sampleId": "synth:warmpad",
      "steps": [
        true, true, true, true, false, false, false, false, true, true, true, false, false, false, true, true
      ],
      "parameterLocks": [
        {"pitch": 0, "volume": 0.8}, {"pitch": 0, "volume": 0.8}, {"pitch": 0, "volume": 0.75}, {"pitch": 0, "volume": 0.7}, null, null, null, null,
        {"pitch": 5, "volume": 0.8}, {"pitch": 5, "volume": 0.75}, {"pitch": 5, "volume": 0.7}, null, null, null, {"pitch": 3, "volume": 0.8}, {"pitch": 3, "volume": 0.75}
      ],
      "volume": 0.5,
      "muted": false,
      "playbackMode": "gate",
      "transpose": 0,
      "stepCount": 16
    },
    {
      "id": "pad-oneshot",
      "name": "Pad ONESHOT",
      "sampleId": "synth:warmpad",
      "steps": [
        true, false, false, false, false, false, false, false, true, false, false, false, false, false, true, false
      ],
      "parameterLocks": [
        {"pitch": 0, "volume": 0.8}, null, null, null, null, null, null, null,
        {"pitch": 5, "volume": 0.8}, null, null, null, null, null, {"pitch": 3, "volume": 0.8}, null
      ],
      "volume": 0.5,
      "muted": true,
      "playbackMode": "oneshot",
      "transpose": 0,
      "stepCount": 16
    },
    {
      "id": "strings-gated",
      "name": "Strings GATE",
      "sampleId": "synth:strings",
      "steps": [
        false, false, false, false, true, true, true, true, true, true, false, false, false, false, false, false,
        false, false, false, false, true, true, true, true, true, true, true, true, false, false, false, false
      ],
      "parameterLocks": [
        null, null, null, null, {"pitch": 7}, {"pitch": 7}, {"pitch": 7}, {"pitch": 7}, {"pitch": 5}, {"pitch": 5}, null, null, null, null, null, null,
        null, null, null, null, {"pitch": 3}, {"pitch": 3}, {"pitch": 3}, {"pitch": 3}, {"pitch": 0}, {"pitch": 0}, {"pitch": 0}, {"pitch": 0}, null, null, null, null
      ],
      "volume": 0.45,
      "muted": false,
      "playbackMode": "gate",
      "transpose": -12,
      "stepCount": 32
    },
    {
      "id": "organ-gated",
      "name": "Organ GATE",
      "sampleId": "synth:organ",
      "steps": [
        true, true, false, false, true, true, true, false, true, true, false, false, true, true, true, true
      ],
      "parameterLocks": [
        {"pitch": 0}, {"pitch": 0}, null, null, {"pitch": 0}, {"pitch": 0}, {"pitch": 0}, null, {"pitch": 5}, {"pitch": 5}, null, null, {"pitch": 3}, {"pitch": 3}, {"pitch": 3}, {"pitch": 3}
      ],
      "volume": 0.4,
      "muted": false,
      "playbackMode": "gate",
      "transpose": 0,
      "stepCount": 16
    },
    {
      "id": "bass-gated",
      "name": "Bass GATE",
      "sampleId": "synth:bass",
      "steps": [
        true, true, false, false, false, false, true, false, true, true, true, false, false, false, true, true
      ],
      "parameterLocks": [
        {"pitch": 0}, {"pitch": 0}, null, null, null, null, {"pitch": 5}, null, {"pitch": 0}, {"pitch": 0}, {"pitch": 0}, null, null, null, {"pitch": -5}, {"pitch": -5}
      ],
      "volume": 0.6,
      "muted": false,
      "playbackMode": "gate",
      "transpose": -12,
      "stepCount": 16
    },
    {
      "id": "lead-staccato",
      "name": "Lead GATE",
      "sampleId": "synth:lead",
      "steps": [
        false, false, true, false, false, false, true, false, false, false, true, true, false, false, true, false
      ],
      "parameterLocks": [
        null, null, {"pitch": 12}, null, null, null, {"pitch": 10}, null, null, null, {"pitch": 8}, {"pitch": 7}, null, null, {"pitch": 5}, null
      ],
      "volume": 0.45,
      "muted": false,
      "playbackMode": "gate",
      "transpose": 0,
      "stepCount": 16
    },
    {
      "id": "hihat-offbeat",
      "name": "Hi-Hat",
      "sampleId": "hihat",
      "steps": [
        false, false, true, false, false, false, true, false, false, false, true, false, false, false, true, false
      ],
      "parameterLocks": [
        null, null, {"volume": 0.6}, null, null, null, {"volume": 0.7}, null, null, null, {"volume": 0.6}, null, null, null, {"volume": 0.7}, null
      ],
      "volume": 0.5,
      "muted": false,
      "playbackMode": "oneshot",
      "transpose": 0,
      "stepCount": 16
    }
  ],
  "tempo": 110,
  "swing": 15
}
